{
  "version": "knowledge-graph-v1",
  "source": "data/knowledge/topic_index.json",
  "scope": "刘辉羽毛球抖音教学视频",
  "source_updated_at": "2026-07-18T01:29:26.221998+00:00",
  "video_count": 406,
  "indexable_video_count": 352,
  "assigned_video_count": 344,
  "multi_topic_video_count": 304,
  "categories": [
    {
      "name": "后场技术",
      "description": "后场击球、被动处理、杀吊突击与架拍框架。",
      "video_count": 217,
      "subtopics": [
        {
          "name": "被动后场与高远",
          "keywords": [
            "被动",
            "高远",
            "后高点",
            "底线",
            "摆脱",
            "反手后场"
          ],
          "video_count": 74,
          "ready_count": 74,
          "representative_videos": [
            {
              "video_id": "7546109410041908538",
              "title": "反手被动高远 虽然被动，但是放松发力更重要，别说示范的球不到位，也打出界一米了，主要是在底线摄像机放不下了",
              "url": "https://www.douyin.com/video/7546109410041908538",
              "confidence": "medium",
              "category": "发力与身体运用",
              "duration_seconds": 225.1,
              "score": 45
            },
            {
              "video_id": "7558912953539071292",
              "title": "被动高远 别说这样容易抡大臂，不这样偷出来时间抢架拍位置也是个输，真被动就没时间侧身，没时间架拍，没空间做…",
              "url": "https://www.douyin.com/video/7558912953539071292",
              "confidence": "curated",
              "category": "后场技术",
              "duration_seconds": 128.9,
              "score": 35
            },
            {
              "video_id": "7491780200468843833",
              "title": "被动位变线 这个位置是比较被动的，主动的在身前的，直接用小臂手腕就可以挡过去",
              "url": "https://www.douyin.com/video/7491780200468843833",
              "confidence": "medium",
              "category": "发力与身体运用",
              "duration_seconds": 52.7,
              "score": 18
            }
          ]
        },
        {
          "name": "杀球、突击与压球",
          "keywords": [
            "杀球",
            "突击",
            "压球",
            "重杀",
            "点杀",
            "落点"
          ],
          "video_count": 73,
          "ready_count": 73,
          "representative_videos": [
            {
              "video_id": "7659348110628345210",
              "title": "杀球瞄准 杀球瞄准 卢迦彧的杀球不是那种很重的，所以落点上就尤为重要，比赛中非常容易被防守反击!中间涉及到…",
              "url": "https://www.douyin.com/video/7659348110628345210",
              "confidence": "curated",
              "category": "后场技术",
              "duration_seconds": 199.3,
              "score": 55
            },
            {
              "video_id": "7567155406117533051",
              "title": "不同杀球 给大家解释为什么每个运动员动作不一样，其实在我的视角里，都是脚蹬地开始发力传递到球拍，但是每个人…",
              "url": "https://www.douyin.com/video/7567155406117533051",
              "confidence": "visual_reviewed",
              "category": "后场技术",
              "duration_seconds": 61.6,
              "score": 15
            },
            {
              "video_id": "7659991105622862457",
              "title": "重杀框架 可以和期一起看，不同的框架可以决定不同的杀球",
              "url": "https://www.douyin.com/video/7659991105622862457",
              "confidence": "medium",
              "category": "后场技术",
              "duration_seconds": 129.7,
              "score": 15
            }
          ]
        },
        {
          "name": "架拍与框架",
          "keywords": [
            "架拍",
            "框架",
            "抬拍",
            "举拍",
            "顶肘"
          ],
          "video_count": 62,
          "ready_count": 62,
          "representative_videos": [
            {
              "video_id": "7589749293205363633",
              "title": "后场框架应用 如果基础好，可以推荐出快速框架，之前发过很多爆发力出框架的作品！但是顶肘动作小带来效率的同时…",
              "url": "https://www.douyin.com/video/7589749293205363633",
              "confidence": "curated",
              "category": "后场技术",
              "duration_seconds": 63.4,
              "score": 58
            },
            {
              "video_id": "7551459420703837498",
              "title": "快速架拍和力量架拍 在两者中间的架拍就是标准的普通架拍，既不会太慢，也不会没力，但是又都做不到极致的快和重…",
              "url": "https://www.douyin.com/video/7551459420703837498",
              "confidence": "medium",
              "category": "后场技术",
              "duration_seconds": 146.3,
              "score": 38
            },
            {
              "video_id": "7658231159860261361",
              "title": "架拍的选择 在两个极端架拍的中间位置，就是最普通的架拍！没有绝对的对错，符合场景，符合自己的情况就是对！",
              "url": "https://www.douyin.com/video/7658231159860261361",
              "confidence": "medium",
              "category": "后场技术",
              "duration_seconds": 108.8,
              "score": 32
            }
          ]
        },
        {
          "name": "吊球与劈吊",
          "keywords": [
            "吊球",
            "劈吊",
            "滑板",
            "假动作"
          ],
          "video_count": 19,
          "ready_count": 19,
          "representative_videos": [
            {
              "video_id": "7427416335900020008",
              "title": "华云纵 入门是实用假动作，熟练后可以发展成花活，去参加职业比赛的朋友不用看后面的",
              "url": "https://www.douyin.com/video/7427416335900020008",
              "confidence": "medium",
              "category": "训练与纠错",
              "duration_seconds": 87.4,
              "score": 12
            },
            {
              "video_id": "7061422431386324264",
              "title": "假动作可以不用，但是不能不会哦，要不拿什么耍帅😂，喜欢的留言直播间带走",
              "url": "https://www.douyin.com/video/7061422431386324264",
              "confidence": "visual_reviewed",
              "category": "训练与纠错",
              "duration_seconds": 25.4,
              "score": 11
            },
            {
              "video_id": "7115241358255803683",
              "title": "吊球和刹球要相互配合使用，拉扯对手防守的站位，一味的强攻很容易被防反",
              "url": "https://www.douyin.com/video/7115241358255803683",
              "confidence": "visual_reviewed",
              "category": "后场技术",
              "duration_seconds": 33.5,
              "score": 11
            }
          ]
        },
        {
          "name": "反手后场",
          "keywords": [
            "反手",
            "反拍",
            "反手高远"
          ],
          "video_count": 75,
          "ready_count": 75,
          "representative_videos": [
            {
              "video_id": "7060717442825309480",
              "title": "反手动作不唯一，但是这种好上手，击球点在转过去的身前外侧",
              "url": "https://www.douyin.com/video/7060717442825309480",
              "confidence": "visual_reviewed",
              "category": "握拍与基本动作",
              "duration_seconds": 93.0,
              "score": 32
            },
            {
              "video_id": "7535400692573211962",
              "title": "反手高远 这个大臂啊，用的越精炼越好，越多越完蛋",
              "url": "https://www.douyin.com/video/7535400692573211962",
              "confidence": "medium",
              "category": "训练与纠错",
              "duration_seconds": 86.6,
              "score": 24
            },
            {
              "video_id": "7055859367005949187",
              "title": "反手高远忘记瞄边了，无视落点😂，技术入门介绍结束，后面会做更细致的教学，粉丝群499184449764",
              "url": "https://www.douyin.com/video/7055859367005949187",
              "confidence": "medium",
              "category": "单打战术",
              "duration_seconds": 66.5,
              "score": 22
            }
          ]
        }
      ]
    },
    {
      "name": "步法与移动",
      "description": "启动、移动、回动、低重心和不同区域步法。",
      "video_count": 92,
      "subtopics": [
        {
          "name": "启动与预动",
          "keywords": [
            "启动",
            "预动",
            "起动",
            "蹬地"
          ],
          "video_count": 28,
          "ready_count": 28,
          "representative_videos": [
            {
              "video_id": "7056244399390412064",
              "title": "分解步法种类繁多，这是练启动有代表性的，一轮一口气做完，做3组。我肯定是没做到10秒钟，要不视频太长😓",
              "url": "https://www.douyin.com/video/7056244399390412064",
              "confidence": "medium",
              "category": "步法与移动",
              "duration_seconds": 123.1,
              "score": 16
            },
            {
              "video_id": "7172742523096517927",
              "title": "腿蹬地，指发力",
              "url": "https://www.douyin.com/video/7172742523096517927",
              "confidence": "medium",
              "category": "发力与身体运用",
              "duration_seconds": 92.6,
              "score": 9
            },
            {
              "video_id": "7309303794733485327",
              "title": "被动也可以用这样的启动方式连接后交叉步",
              "url": "https://www.douyin.com/video/7309303794733485327",
              "confidence": "medium",
              "category": "步法与移动",
              "duration_seconds": 43.1,
              "score": 9
            }
          ]
        },
        {
          "name": "回动与连贯",
          "keywords": [
            "回动",
            "连贯",
            "衔接",
            "下一拍"
          ],
          "video_count": 26,
          "ready_count": 26,
          "representative_videos": [
            {
              "video_id": "7229889111706848544",
              "title": "这属于为了下一拍更好衔接的步法，也是使用率最高的",
              "url": "https://www.douyin.com/video/7229889111706848544",
              "confidence": "medium",
              "category": "发球与接发",
              "duration_seconds": 137.1,
              "score": 18
            },
            {
              "video_id": "7059589039694957864",
              "title": "并不是说一定要一步回位。而是体现向左回动，左脚的重要性",
              "url": "https://www.douyin.com/video/7059589039694957864",
              "confidence": "visual_reviewed",
              "category": "步法与移动",
              "duration_seconds": 72.6,
              "score": 15
            },
            {
              "video_id": "7085169366005714217",
              "title": "1 白鞋白胶布2低重心步法回动3低重心步法训练，这是我自创训练",
              "url": "https://www.douyin.com/video/7085169366005714217",
              "confidence": "medium",
              "category": "步法与移动",
              "duration_seconds": 158.0,
              "score": 12
            }
          ]
        },
        {
          "name": "交叉步与并步",
          "keywords": [
            "交叉步",
            "并步",
            "垫步",
            "步伐"
          ],
          "video_count": 25,
          "ready_count": 25,
          "representative_videos": [
            {
              "video_id": "7643719807951615482",
              "title": "回动步法合理性 每个人的合理也不一样，有的人腿的力量强，并步能并很远，所以还要结合自己的情况",
              "url": "https://www.douyin.com/video/7643719807951615482",
              "confidence": "medium",
              "category": "步法与移动",
              "duration_seconds": 131.8,
              "score": 15
            },
            {
              "video_id": "7064753436809514281",
              "title": "发个老库存，垫步和并步都接双脚起跳的合适步法",
              "url": "https://www.douyin.com/video/7064753436809514281",
              "confidence": "medium",
              "category": "步法与移动",
              "duration_seconds": 37.5,
              "score": 12
            },
            {
              "video_id": "7065157571816000809",
              "title": "今天偷懒，晚上见，发个没音乐的，纯粹目的杀上网就是交叉步，",
              "url": "https://www.douyin.com/video/7065157571816000809",
              "confidence": "visual_reviewed",
              "category": "步法与移动",
              "duration_seconds": 19.6,
              "score": 10
            }
          ]
        },
        {
          "name": "低重心与被动救球",
          "keywords": [
            "低重心",
            "被动步法",
            "救球",
            "重心"
          ],
          "video_count": 43,
          "ready_count": 43,
          "representative_videos": [
            {
              "video_id": "7085169366005714217",
              "title": "1 白鞋白胶布2低重心步法回动3低重心步法训练，这是我自创训练",
              "url": "https://www.douyin.com/video/7085169366005714217",
              "confidence": "medium",
              "category": "步法与移动",
              "duration_seconds": 158.0,
              "score": 55
            },
            {
              "video_id": "7185360811248864544",
              "title": "就像跑步重心要在前面，倒退跑重心要在后面一样",
              "url": "https://www.douyin.com/video/7185360811248864544",
              "confidence": "medium",
              "category": "步法与移动",
              "duration_seconds": 75.4,
              "score": 17
            },
            {
              "video_id": "7141570854437063977",
              "title": "总结，看对方的重心有没有丢失，如果进攻的效果好，对手重心没了，肯定还是可以勾的",
              "url": "https://www.douyin.com/video/7141570854437063977",
              "confidence": "medium",
              "category": "步法与移动",
              "duration_seconds": 91.3,
              "score": 12
            }
          ]
        },
        {
          "name": "正手区与网前步法",
          "keywords": [
            "正手区",
            "网前步法",
            "上网",
            "前后步法"
          ],
          "video_count": 19,
          "ready_count": 19,
          "representative_videos": [
            {
              "video_id": "7567860375287303035",
              "title": "正手区前后步法（基础版） 正手区前后步法种类非常多，这是一种比较简单合理的步法，而且教学对象是左手，左右手…",
              "url": "https://www.douyin.com/video/7567860375287303035",
              "confidence": "medium",
              "category": "步法与移动",
              "duration_seconds": 351.7,
              "score": 36
            },
            {
              "video_id": "7406541084219821312",
              "title": "正手网前步法 当然还要注意左手的摆放和重心的控制，但是时间有限，直播的时候讲吧",
              "url": "https://www.douyin.com/video/7406541084219821312",
              "confidence": "medium",
              "category": "网前技术",
              "duration_seconds": 126.9,
              "score": 11
            },
            {
              "video_id": "7142313105324870950",
              "title": "s上网小飞侠“两步一冲”，曹植当年要有这样的七步早就蹬出皇宫了！",
              "url": "https://www.douyin.com/video/7142313105324870950",
              "confidence": "medium",
              "category": "训练与纠错",
              "duration_seconds": 129.5,
              "score": 9
            }
          ]
        }
      ]
    },
    {
      "name": "发力与身体运用",
      "description": "放松发力、旋转传导、腰腹、手腕与击球发力区间。",
      "video_count": 237,
      "subtopics": [
        {
          "name": "放松与爆发",
          "keywords": [
            "放松",
            "爆发",
            "发力",
            "打透"
          ],
          "video_count": 136,
          "ready_count": 136,
          "representative_videos": [
            {
              "video_id": "7628342769941691121",
              "title": "放松架拍 没有说对错，是很多人还不会自然传动力量就开始锁定身体，锁住力量是为了让会发力的人爆发力最大化，不…",
              "url": "https://www.douyin.com/video/7628342769941691121",
              "confidence": "medium",
              "category": "后场技术",
              "duration_seconds": 71.0,
              "score": 48
            },
            {
              "video_id": "7097047150479084835",
              "title": "手指是末梢的发力，前面还需要很多带动，食指拇指都需要发力，只不过是支撑",
              "url": "https://www.douyin.com/video/7097047150479084835",
              "confidence": "medium",
              "category": "发力与身体运用",
              "duration_seconds": 147.8,
              "score": 28
            },
            {
              "video_id": "7052600326116887812",
              "title": "00:00 / 00:47 后场发力下集，由下到上一步一步带动全身协调发力，发力为外旋，不会伤手腕，伤手腕…",
              "url": "https://www.douyin.com/video/7052600326116887812",
              "confidence": "medium",
              "category": "后场技术",
              "duration_seconds": 47.4,
              "score": 27
            }
          ]
        },
        {
          "name": "腰腹与身体旋转",
          "keywords": [
            "腰腹",
            "核心",
            "旋转",
            "转体",
            "身体"
          ],
          "video_count": 91,
          "ready_count": 91,
          "representative_videos": [
            {
              "video_id": "7494729488699559225",
              "title": "腰腹发力 手放好位置，感受腰腹发力的方向，只有把方向做对，击球才能有效果",
              "url": "https://www.douyin.com/video/7494729488699559225",
              "confidence": "medium",
              "category": "发力与身体运用",
              "duration_seconds": 36.0,
              "score": 25
            },
            {
              "video_id": "7067722128413543680",
              "title": "一定要3集看完再去练啊😂霸王杀就是尽可能的让动作最高效，爆发力最大化，出手快动作小，易衔接，重心摇摆小等特…",
              "url": "https://www.douyin.com/video/7067722128413543680",
              "confidence": "medium",
              "category": "步法与移动",
              "duration_seconds": 210.1,
              "score": 20
            },
            {
              "video_id": "7592181557051310961",
              "title": "女生反手发力 身体代偿力量，手指手腕集中介入，身体要转的快补拍速",
              "url": "https://www.douyin.com/video/7592181557051310961",
              "confidence": "medium",
              "category": "发力与身体运用",
              "duration_seconds": 182.7,
              "score": 16
            }
          ]
        },
        {
          "name": "手腕、内旋与拍面",
          "keywords": [
            "手腕",
            "内旋",
            "拍面",
            "握拍"
          ],
          "video_count": 118,
          "ready_count": 118,
          "representative_videos": [
            {
              "video_id": "7146762792438074665",
              "title": "握拍从准备握拍，向右旋转直至虎口对着正拍面，或接近正拍面",
              "url": "https://www.douyin.com/video/7146762792438074665",
              "confidence": "medium",
              "category": "握拍与基本动作",
              "duration_seconds": 33.3,
              "score": 41
            },
            {
              "video_id": "7086276287681137961",
              "title": "半拳式握拍是发力必备的握拍，没有半拳式，基本出现不了鞭甩，因为大拇指会卡住",
              "url": "https://www.douyin.com/video/7086276287681137961",
              "confidence": "medium",
              "category": "发力与身体运用",
              "duration_seconds": 71.6,
              "score": 23
            },
            {
              "video_id": "7570301879545426171",
              "title": "发力细节 每个人的情况不一样，我告诉抡大臂的人要用小臂，告诉内旋挥不正的人压手腕，不过他 但凡能做对一点，…",
              "url": "https://www.douyin.com/video/7570301879545426171",
              "confidence": "medium",
              "category": "后场技术",
              "duration_seconds": 202.5,
              "score": 23
            }
          ]
        },
        {
          "name": "贴球发力",
          "keywords": [
            "贴球",
            "贴近",
            "发力空间"
          ],
          "video_count": 8,
          "ready_count": 8,
          "representative_videos": [
            {
              "video_id": "7440406891664133428",
              "title": "压球新讲 就算追求贴球发力，也得是建立在能把动作做完的基础上贴，怕打不到球也会本能的把球拍接近球而失去发力…",
              "url": "https://www.douyin.com/video/7440406891664133428",
              "confidence": "medium",
              "category": "发力与身体运用",
              "duration_seconds": 72.5,
              "score": 15
            },
            {
              "video_id": "7145708380047297833",
              "title": "兄弟们也可以看往期的手指发力，贴球发力来做铺垫",
              "url": "https://www.douyin.com/video/7145708380047297833",
              "confidence": "medium",
              "category": "发力与身体运用",
              "duration_seconds": 75.7,
              "score": 8
            },
            {
              "video_id": "7071068959021255951",
              "title": "学好停顿，可以衔接很多动作哦，而且可以改变比赛的节奏，成为节奏大师👍🏻",
              "url": "https://www.douyin.com/video/7071068959021255951",
              "confidence": "medium",
              "category": "单打战术",
              "duration_seconds": 55.6,
              "score": 2
            }
          ]
        },
        {
          "name": "挥拍路径",
          "keywords": [
            "挥拍",
            "随挥",
            "半程",
            "全程",
            "大臂"
          ],
          "video_count": 82,
          "ready_count": 82,
          "representative_videos": [
            {
              "video_id": "7383154379915906319",
              "title": "基础挥拍重快 由于要控制时长我剪辑的很精简，基础挥拍如何打的重，如何打的快，建议多看两边，详细的我们直播间…",
              "url": "https://www.douyin.com/video/7383154379915906319",
              "confidence": "medium",
              "category": "后场技术",
              "duration_seconds": 200.7,
              "score": 27
            },
            {
              "video_id": "7170144521781562662",
              "title": "一切的根源都是大臂走的太多失去了甩小臂的目的",
              "url": "https://www.douyin.com/video/7170144521781562662",
              "confidence": "medium",
              "category": "发力与身体运用",
              "duration_seconds": 91.2,
              "score": 23
            },
            {
              "video_id": "7322291358931127592",
              "title": "不用管身高，网带能卡住大臂就行在哪卡都可以，用网带辅助不依赖大臂挥下去",
              "url": "https://www.douyin.com/video/7322291358931127592",
              "confidence": "medium",
              "category": "训练与纠错",
              "duration_seconds": 162.3,
              "score": 22
            }
          ]
        }
      ]
    },
    {
      "name": "中前场与抽挡",
      "description": "抽挡、接杀、防守、网前技术和中前场转换。",
      "video_count": 106,
      "subtopics": [
        {
          "name": "平抽挡与高速对抗",
          "keywords": [
            "抽挡",
            "平抽挡",
            "高速对抗",
            "快球"
          ],
          "video_count": 6,
          "ready_count": 6,
          "representative_videos": [
            {
              "video_id": "7652440366436945017",
              "title": "高速对抗步法 小姐姐是两省冠军🏆，这种情况属于高速对抗状态下，就是球都比较平，没有侧身的时间和意义",
              "url": "https://www.douyin.com/video/7652440366436945017",
              "confidence": "medium",
              "category": "步法与移动",
              "duration_seconds": 298.4,
              "score": 16
            },
            {
              "video_id": "7447084061371272507",
              "title": "握拍微调 抽挡反手为主，尽量不做正反手转换",
              "url": "https://www.douyin.com/video/7447084061371272507",
              "confidence": "visual_reviewed",
              "category": "中前场与抽挡",
              "duration_seconds": 34.5,
              "score": 15
            },
            {
              "video_id": "7506736569824726332",
              "title": "抽挡连贯 我知道有些兄弟很要强，受不了这种屈辱，就是不能承认被动，没关系，打羽毛球吧，它一定会教会你",
              "url": "https://www.douyin.com/video/7506736569824726332",
              "confidence": "medium",
              "category": "中前场与抽挡",
              "duration_seconds": 109.1,
              "score": 9
            }
          ]
        },
        {
          "name": "接杀与防守",
          "keywords": [
            "接杀",
            "防守",
            "防反",
            "挡杀"
          ],
          "video_count": 39,
          "ready_count": 39,
          "representative_videos": [
            {
              "video_id": "7621243051541587889",
              "title": "双打防守思路 你总会遇到你挑不起来的进攻",
              "url": "https://www.douyin.com/video/7621243051541587889",
              "confidence": "medium",
              "category": "双打战术",
              "duration_seconds": 113.9,
              "score": 18
            },
            {
              "video_id": "7586613438625959217",
              "title": "单打防守 主要在于省步子，和好衔接，当对方球速非常快的时候就只能这样接了",
              "url": "https://www.douyin.com/video/7586613438625959217",
              "confidence": "medium",
              "category": "单打战术",
              "duration_seconds": 153.8,
              "score": 15
            },
            {
              "video_id": "7115241358255803683",
              "title": "吊球和刹球要相互配合使用，拉扯对手防守的站位，一味的强攻很容易被防反",
              "url": "https://www.douyin.com/video/7115241358255803683",
              "confidence": "visual_reviewed",
              "category": "后场技术",
              "duration_seconds": 33.5,
              "score": 14
            }
          ]
        },
        {
          "name": "网前搓勾扑",
          "keywords": [
            "网前",
            "搓球",
            "勾球",
            "扑球",
            "滚网"
          ],
          "video_count": 47,
          "ready_count": 47,
          "representative_videos": [
            {
              "video_id": "7509355373729762619",
              "title": "滚网搓球 双打网前有人看守时有奇效",
              "url": "https://www.douyin.com/video/7509355373729762619",
              "confidence": "medium",
              "category": "网前技术",
              "duration_seconds": 77.3,
              "score": 31
            },
            {
              "video_id": "7064010057020673314",
              "title": "身前位勾球，和侧身位的勾球不一样，正手也存在变拍，只不过没反手那么需要",
              "url": "https://www.douyin.com/video/7064010057020673314",
              "confidence": "medium",
              "category": "网前技术",
              "duration_seconds": 88.6,
              "score": 25
            },
            {
              "video_id": "7231373527314631947",
              "title": "不是说勾球不能带过去，是不能大臂和球拍一起过去，如果学不会，就先练简单的勾球，这属于进阶",
              "url": "https://www.douyin.com/video/7231373527314631947",
              "confidence": "medium",
              "category": "发球与接发",
              "duration_seconds": 123.4,
              "score": 23
            }
          ]
        },
        {
          "name": "挡网与放网",
          "keywords": [
            "挡网",
            "放网",
            "网前球"
          ],
          "video_count": 14,
          "ready_count": 14,
          "representative_videos": [
            {
              "video_id": "7524557392328461627",
              "title": "挡网 我最近发的东西都是大家认为简单，但是一点不简单的东西",
              "url": "https://www.douyin.com/video/7524557392328461627",
              "confidence": "medium",
              "category": "中前场与抽挡",
              "duration_seconds": 208.6,
              "score": 12
            },
            {
              "video_id": "7106697344128748835",
              "title": "中腰球出来，出现轮转的可能性很大",
              "url": "https://www.douyin.com/video/7106697344128748835",
              "confidence": "medium",
              "category": "双打战术",
              "duration_seconds": 91.7,
              "score": 10
            },
            {
              "video_id": "7092959332047785250",
              "title": "也不要问为什么不放网，对方远网球这个不可能去钓鱼失误率太高，也不能挡远网，惯性大没办法抓推",
              "url": "https://www.douyin.com/video/7092959332047785250",
              "confidence": "medium",
              "category": "网前技术",
              "duration_seconds": 93.6,
              "score": 9
            }
          ]
        },
        {
          "name": "中前场衔接",
          "keywords": [
            "中前场",
            "衔接",
            "连贯",
            "封网"
          ],
          "video_count": 16,
          "ready_count": 16,
          "representative_videos": [
            {
              "video_id": "7278130800220998946",
              "title": "一个小小的方向改变就可以让进攻衔接的更加流畅",
              "url": "https://www.douyin.com/video/7278130800220998946",
              "confidence": "medium",
              "category": "发球与接发",
              "duration_seconds": 89.4,
              "score": 9
            },
            {
              "video_id": "7607852875611759802",
              "title": "压迫位封网 祝大家新年快乐！大年初二也不要忘记研究羽毛球啊！",
              "url": "https://www.douyin.com/video/7607852875611759802",
              "confidence": "medium",
              "category": "中前场与抽挡",
              "duration_seconds": 88.7,
              "score": 9
            },
            {
              "video_id": "7506736569824726332",
              "title": "抽挡连贯 我知道有些兄弟很要强，受不了这种屈辱，就是不能承认被动，没关系，打羽毛球吧，它一定会教会你",
              "url": "https://www.douyin.com/video/7506736569824726332",
              "confidence": "medium",
              "category": "中前场与抽挡",
              "duration_seconds": 109.1,
              "score": 9
            }
          ]
        }
      ]
    },
    {
      "name": "双打战术",
      "description": "双打轮转、防守站位、封网、进攻组织和发接发配合。",
      "video_count": 56,
      "subtopics": [
        {
          "name": "双打发接发",
          "keywords": [
            "双打发接发",
            "接发",
            "发接发",
            "抓球"
          ],
          "video_count": 6,
          "ready_count": 6,
          "representative_videos": [
            {
              "video_id": "7501542236061420859",
              "title": "双打发接发 永远考虑对手出球最快的位置，慢的位置球真来了再说",
              "url": "https://www.douyin.com/video/7501542236061420859",
              "confidence": "medium",
              "category": "发球与接发",
              "duration_seconds": 86.5,
              "score": 27
            },
            {
              "video_id": "7639306481355832689",
              "title": "接发准备 每个人都要清楚做动作的目的性，不能盲目学习",
              "url": "https://www.douyin.com/video/7639306481355832689",
              "confidence": "medium",
              "category": "发球与接发",
              "duration_seconds": 127.8,
              "score": 10
            },
            {
              "video_id": "7475440958130097466",
              "title": "教学联动 我和彭教练用这样演绎的方式来讲发球的抓球思路，但是我本人叛逆者的形象是想告诉大家战术是固定的，人…",
              "url": "https://www.douyin.com/video/7475440958130097466",
              "confidence": "medium",
              "category": "发球与接发",
              "duration_seconds": 155.4,
              "score": 9
            }
          ]
        },
        {
          "name": "轮转与补位",
          "keywords": [
            "轮转",
            "补位",
            "前后",
            "左右"
          ],
          "video_count": 12,
          "ready_count": 12,
          "representative_videos": [
            {
              "video_id": "7567860375287303035",
              "title": "正手区前后步法（基础版） 正手区前后步法种类非常多，这是一种比较简单合理的步法，而且教学对象是左手，左右手…",
              "url": "https://www.douyin.com/video/7567860375287303035",
              "confidence": "medium",
              "category": "步法与移动",
              "duration_seconds": 351.7,
              "score": 24
            },
            {
              "video_id": "7614167503938610417",
              "title": "双打实战轮转 无论训练时有多么默契，实战中都会有配合失误，那实战看的就是两个人的容错够不够",
              "url": "https://www.douyin.com/video/7614167503938610417",
              "confidence": "medium",
              "category": "双打战术",
              "duration_seconds": 156.5,
              "score": 15
            },
            {
              "video_id": "7054395778814561575",
              "title": "做两期前后场一致性的视频，你们知道用的都是那种技术嘛？后面有入门讲解，教学后期出，或者直播的时候讲吧，东西…",
              "url": "https://www.douyin.com/video/7054395778814561575",
              "confidence": "medium",
              "category": "后场技术",
              "duration_seconds": 52.2,
              "score": 9
            }
          ]
        },
        {
          "name": "双打防守站位",
          "keywords": [
            "双打防守",
            "防守站位",
            "平行",
            "护边"
          ],
          "video_count": 6,
          "ready_count": 6,
          "representative_videos": [
            {
              "video_id": "7621243051541587889",
              "title": "双打防守思路 你总会遇到你挑不起来的进攻",
              "url": "https://www.douyin.com/video/7621243051541587889",
              "confidence": "medium",
              "category": "双打战术",
              "duration_seconds": 113.9,
              "score": 9
            },
            {
              "video_id": "7414339897990843663",
              "title": "双打防守进阶 外旋是大臂带动小臂的必然动作，用手指发力也可以，但是非常考验力量",
              "url": "https://www.douyin.com/video/7414339897990843663",
              "confidence": "medium",
              "category": "后场技术",
              "duration_seconds": 121.8,
              "score": 9
            },
            {
              "video_id": "7065491791167999232",
              "title": "挥拍路径向斜下方就是保证球尽可能的会平，任何网前高位都可以用，球平行过网了注意抓对手推球",
              "url": "https://www.douyin.com/video/7065491791167999232",
              "confidence": "medium",
              "category": "后场技术",
              "duration_seconds": 32.2,
              "score": 6
            }
          ]
        },
        {
          "name": "封网与抢网",
          "keywords": [
            "封网",
            "抢网",
            "前场"
          ],
          "video_count": 9,
          "ready_count": 9,
          "representative_videos": [
            {
              "video_id": "7095554075210550528",
              "title": "摇摆球对付抢网凶狠的对手，如果对方不抢网就没什么用啦😂",
              "url": "https://www.douyin.com/video/7095554075210550528",
              "confidence": "medium",
              "category": "训练与纠错",
              "duration_seconds": 63.6,
              "score": 15
            },
            {
              "video_id": "7607852875611759802",
              "title": "压迫位封网 祝大家新年快乐！大年初二也不要忘记研究羽毛球啊！",
              "url": "https://www.douyin.com/video/7607852875611759802",
              "confidence": "medium",
              "category": "中前场与抽挡",
              "duration_seconds": 88.7,
              "score": 9
            },
            {
              "video_id": "7127470220309957923",
              "title": "模拟的防守挡斜线随后抢网反击",
              "url": "https://www.douyin.com/video/7127470220309957923",
              "confidence": "medium",
              "category": "训练与纠错",
              "duration_seconds": 55.0,
              "score": 9
            }
          ]
        },
        {
          "name": "进攻组织",
          "keywords": [
            "进攻",
            "组织",
            "压制",
            "后杀前封"
          ],
          "video_count": 32,
          "ready_count": 32,
          "representative_videos": [
            {
              "video_id": "7278130800220998946",
              "title": "一个小小的方向改变就可以让进攻衔接的更加流畅",
              "url": "https://www.douyin.com/video/7278130800220998946",
              "confidence": "medium",
              "category": "发球与接发",
              "duration_seconds": 89.4,
              "score": 18
            },
            {
              "video_id": "7619576226616745445",
              "title": "双打进攻思路 抛砖引玉，场景太多，整体就是要根据自己和队友的位置去考虑",
              "url": "https://www.douyin.com/video/7619576226616745445",
              "confidence": "medium",
              "category": "双打战术",
              "duration_seconds": 111.6,
              "score": 13
            },
            {
              "video_id": "7384641787647872308",
              "title": "组织框架 还有很多没补充上，时间有限，简单介绍下，放松展开的架拍是只有要击球了我们展开，快速架拍是启动就展…",
              "url": "https://www.douyin.com/video/7384641787647872308",
              "confidence": "medium",
              "category": "后场技术",
              "duration_seconds": 74.8,
              "score": 10
            }
          ]
        }
      ]
    },
    {
      "name": "发球与接发",
      "description": "单打与双打发球、接发、发接发目的性。",
      "video_count": 60,
      "subtopics": [
        {
          "name": "发球",
          "keywords": [
            "发球",
            "发小球",
            "偷后场"
          ],
          "video_count": 32,
          "ready_count": 32,
          "representative_videos": [
            {
              "video_id": "7254755365995285812",
              "title": "正手发小球的教学，以前的作品里有，没有好的发球，只有合适的发球",
              "url": "https://www.douyin.com/video/7254755365995285812",
              "confidence": "medium",
              "category": "发球与接发",
              "duration_seconds": 114.8,
              "score": 29
            },
            {
              "video_id": "7626127268884067249",
              "title": "保姆级反手发球教学 首先就是这三位都是年训学员，天天在一起关系比较好，所以说话自由一点，大家不要喷我！再一…",
              "url": "https://www.douyin.com/video/7626127268884067249",
              "confidence": "medium",
              "category": "发球与接发",
              "duration_seconds": 345.6,
              "score": 19
            },
            {
              "video_id": "7483346020332522812",
              "title": "发球变化 发球隐蔽是非常重要的",
              "url": "https://www.douyin.com/video/7483346020332522812",
              "confidence": "medium",
              "category": "发球与接发",
              "duration_seconds": 27.7,
              "score": 19
            }
          ]
        },
        {
          "name": "接发",
          "keywords": [
            "接发",
            "接发球",
            "抢发"
          ],
          "video_count": 5,
          "ready_count": 5,
          "representative_videos": [
            {
              "video_id": "7639306481355832689",
              "title": "接发准备 每个人都要清楚做动作的目的性，不能盲目学习",
              "url": "https://www.douyin.com/video/7639306481355832689",
              "confidence": "medium",
              "category": "发球与接发",
              "duration_seconds": 127.8,
              "score": 10
            },
            {
              "video_id": "7501542236061420859",
              "title": "双打发接发 永远考虑对手出球最快的位置，慢的位置球真来了再说",
              "url": "https://www.douyin.com/video/7501542236061420859",
              "confidence": "medium",
              "category": "发球与接发",
              "duration_seconds": 86.5,
              "score": 9
            },
            {
              "video_id": "7271452082337598760",
              "title": "课堂随录的，比平时唠叨些，需要的朋友自取",
              "url": "https://www.douyin.com/video/7271452082337598760",
              "confidence": "medium",
              "category": "训练与纠错",
              "duration_seconds": 168.5,
              "score": 6
            }
          ]
        },
        {
          "name": "发接发目的性",
          "keywords": [
            "目的性",
            "抓球",
            "主动",
            "限制"
          ],
          "video_count": 32,
          "ready_count": 32,
          "representative_videos": [
            {
              "video_id": "7300032085358660904",
              "title": "打球要有目的性，更要清楚对手的目的性",
              "url": "https://www.douyin.com/video/7300032085358660904",
              "confidence": "medium",
              "category": "训练与纠错",
              "duration_seconds": 184.4,
              "score": 15
            },
            {
              "video_id": "7072543702161296640",
              "title": "双打发球如何争取主动，就是规则高度内能拿多高拿多高，球能拿多前就拿多前😂",
              "url": "https://www.douyin.com/video/7072543702161296640",
              "confidence": "medium",
              "category": "发球与接发",
              "duration_seconds": 42.2,
              "score": 11
            },
            {
              "video_id": "7558912953539071292",
              "title": "被动高远 别说这样容易抡大臂，不这样偷出来时间抢架拍位置也是个输，真被动就没时间侧身，没时间架拍，没空间做…",
              "url": "https://www.douyin.com/video/7558912953539071292",
              "confidence": "curated",
              "category": "后场技术",
              "duration_seconds": 128.9,
              "score": 10
            }
          ]
        }
      ]
    },
    {
      "name": "训练与纠错",
      "description": "训练设计、常见错误、实战复盘和恢复对抗能力。",
      "video_count": 157,
      "subtopics": [
        {
          "name": "训练方法",
          "keywords": [
            "训练",
            "练习",
            "多球",
            "三步",
            "方法"
          ],
          "video_count": 58,
          "ready_count": 58,
          "representative_videos": [
            {
              "video_id": "7085169366005714217",
              "title": "1 白鞋白胶布2低重心步法回动3低重心步法训练，这是我自创训练",
              "url": "https://www.douyin.com/video/7085169366005714217",
              "confidence": "medium",
              "category": "步法与移动",
              "duration_seconds": 158.0,
              "score": 25
            },
            {
              "video_id": "7541623926234811705",
              "title": "反手高远球 提供一个训练方法，方法不唯一",
              "url": "https://www.douyin.com/video/7541623926234811705",
              "confidence": "medium",
              "category": "后场技术",
              "duration_seconds": 136.5,
              "score": 25
            },
            {
              "video_id": "7432633273060314408",
              "title": "如何快速恢复对抗能力 觉得训练的时候实在不行了，就可以直接最后一个项目了",
              "url": "https://www.douyin.com/video/7432633273060314408",
              "confidence": "medium",
              "category": "训练与纠错",
              "duration_seconds": 184.0,
              "score": 25
            }
          ]
        },
        {
          "name": "常见错误纠正",
          "keywords": [
            "错误",
            "不对",
            "纠正",
            "问题"
          ],
          "video_count": 97,
          "ready_count": 97,
          "representative_videos": [
            {
              "video_id": "7492357671853526329",
              "title": "爆改球友 转髋还有问题，不过可以先熟悉动作了，其他的问题可以有了转髋后再微调",
              "url": "https://www.douyin.com/video/7492357671853526329",
              "confidence": "medium",
              "category": "训练与纠错",
              "duration_seconds": 273.3,
              "score": 19
            },
            {
              "video_id": "7530102529830800699",
              "title": "挥拍方向 一定要让身边有这个问题的朋友看，根据长期线下培训的数据看，超过60%的球友有这样的问题",
              "url": "https://www.douyin.com/video/7530102529830800699",
              "confidence": "medium",
              "category": "后场技术",
              "duration_seconds": 137.3,
              "score": 16
            },
            {
              "video_id": "7540508309087358266",
              "title": "日常纠错 快让有这个问题的朋友们看看吧",
              "url": "https://www.douyin.com/video/7540508309087358266",
              "confidence": "medium",
              "category": "训练与纠错",
              "duration_seconds": 68.5,
              "score": 13
            }
          ]
        },
        {
          "name": "实战复盘",
          "keywords": [
            "实战",
            "战术",
            "复盘",
            "比赛"
          ],
          "video_count": 35,
          "ready_count": 35,
          "representative_videos": [
            {
              "video_id": "7614167503938610417",
              "title": "双打实战轮转 无论训练时有多么默契，实战中都会有配合失误，那实战看的就是两个人的容错够不够",
              "url": "https://www.douyin.com/video/7614167503938610417",
              "confidence": "medium",
              "category": "双打战术",
              "duration_seconds": 156.5,
              "score": 22
            },
            {
              "video_id": "7252154554828033295",
              "title": "第一局双方都在摸索，失误都比较多，因为在引领节奏，所以我消耗更大，第二局都是多拍了，黄教练也在一直拆解我的…",
              "url": "https://www.douyin.com/video/7252154554828033295",
              "confidence": "medium",
              "category": "单打战术",
              "duration_seconds": 603.5,
              "score": 18
            },
            {
              "video_id": "7094072057608047913",
              "title": "今天本来想拍教学的，但是人手不够😂，内涵一下某地区比赛，大家知道是哪里嘛？",
              "url": "https://www.douyin.com/video/7094072057608047913",
              "confidence": "medium",
              "category": "训练与纠错",
              "duration_seconds": 74.1,
              "score": 11
            }
          ]
        },
        {
          "name": "恢复与体能",
          "keywords": [
            "恢复",
            "体能",
            "对抗能力",
            "精疲力尽"
          ],
          "video_count": 4,
          "ready_count": 4,
          "representative_videos": [
            {
              "video_id": "7432633273060314408",
              "title": "如何快速恢复对抗能力 觉得训练的时候实在不行了，就可以直接最后一个项目了",
              "url": "https://www.douyin.com/video/7432633273060314408",
              "confidence": "medium",
              "category": "训练与纠错",
              "duration_seconds": 184.0,
              "score": 28
            },
            {
              "video_id": "7099644893269839144",
              "title": "职业运动员上网因为身体能力强，大部分采用跨步，但是依然每局还是能见到垫步的出现",
              "url": "https://www.douyin.com/video/7099644893269839144",
              "confidence": "medium",
              "category": "训练与纠错",
              "duration_seconds": 91.7,
              "score": 10
            },
            {
              "video_id": "7193151905139395872",
              "title": "今天恢复直播。就算压不住，也有效果，遇到平高有条件直接反加速",
              "url": "https://www.douyin.com/video/7193151905139395872",
              "confidence": "medium",
              "category": "训练与纠错",
              "duration_seconds": 127.0,
              "score": 9
            }
          ]
        }
      ]
    },
    {
      "name": "握拍与基本动作",
      "description": "握拍、基础挥拍、基础动作和拍面控制。",
      "video_count": 117,
      "subtopics": [
        {
          "name": "握拍",
          "keywords": [
            "握拍",
            "正手握拍",
            "反手握拍"
          ],
          "video_count": 31,
          "ready_count": 31,
          "representative_videos": [
            {
              "video_id": "7086276287681137961",
              "title": "半拳式握拍是发力必备的握拍，没有半拳式，基本出现不了鞭甩，因为大拇指会卡住",
              "url": "https://www.douyin.com/video/7086276287681137961",
              "confidence": "medium",
              "category": "发力与身体运用",
              "duration_seconds": 71.6,
              "score": 23
            },
            {
              "video_id": "7146762792438074665",
              "title": "握拍从准备握拍，向右旋转直至虎口对着正拍面，或接近正拍面",
              "url": "https://www.douyin.com/video/7146762792438074665",
              "confidence": "medium",
              "category": "握拍与基本动作",
              "duration_seconds": 33.3,
              "score": 18
            },
            {
              "video_id": "7447084061371272507",
              "title": "握拍微调 抽挡反手为主，尽量不做正反手转换",
              "url": "https://www.douyin.com/video/7447084061371272507",
              "confidence": "visual_reviewed",
              "category": "中前场与抽挡",
              "duration_seconds": 34.5,
              "score": 17
            }
          ]
        },
        {
          "name": "基础挥拍",
          "keywords": [
            "基础挥拍",
            "挥拍",
            "随摆"
          ],
          "video_count": 34,
          "ready_count": 34,
          "representative_videos": [
            {
              "video_id": "7383154379915906319",
              "title": "基础挥拍重快 由于要控制时长我剪辑的很精简，基础挥拍如何打的重，如何打的快，建议多看两边，详细的我们直播间…",
              "url": "https://www.douyin.com/video/7383154379915906319",
              "confidence": "medium",
              "category": "后场技术",
              "duration_seconds": 200.7,
              "score": 43
            },
            {
              "video_id": "7453420876076240188",
              "title": "基础挥拍 可以当网课看了，@ 你不会挥拍的小伙伴来看吧",
              "url": "https://www.douyin.com/video/7453420876076240188",
              "confidence": "medium",
              "category": "后场技术",
              "duration_seconds": 1226.9,
              "score": 29
            },
            {
              "video_id": "7102635326803332393",
              "title": "向前的挥拍，可以使挥拍的力最高效的发挥",
              "url": "https://www.douyin.com/video/7102635326803332393",
              "confidence": "medium",
              "category": "后场技术",
              "duration_seconds": 73.8,
              "score": 17
            }
          ]
        },
        {
          "name": "拍面控制",
          "keywords": [
            "拍面",
            "角度",
            "控制"
          ],
          "video_count": 72,
          "ready_count": 72,
          "representative_videos": [
            {
              "video_id": "7060717442825309480",
              "title": "反手动作不唯一，但是这种好上手，击球点在转过去的身前外侧",
              "url": "https://www.douyin.com/video/7060717442825309480",
              "confidence": "visual_reviewed",
              "category": "握拍与基本动作",
              "duration_seconds": 93.0,
              "score": 20
            },
            {
              "video_id": "7146762792438074665",
              "title": "握拍从准备握拍，向右旋转直至虎口对着正拍面，或接近正拍面",
              "url": "https://www.douyin.com/video/7146762792438074665",
              "confidence": "medium",
              "category": "握拍与基本动作",
              "duration_seconds": 33.3,
              "score": 17
            },
            {
              "video_id": "7064372942880148777",
              "title": "这个实战很行，击球点在额头前或上一个头的位置",
              "url": "https://www.douyin.com/video/7064372942880148777",
              "confidence": "medium",
              "category": "握拍与基本动作",
              "duration_seconds": 49.9,
              "score": 11
            }
          ]
        }
      ]
    }
  ]
}
